{
  "$schema": "https://developer.microsoft.com/json-schemas/spfx/client-side-web-part-manifest.schema.json",
  "id": "c48067e0-93d4-4f67-9271-f67b617b715f",
  "alias": "CloudPlatformWebPart",
  "componentType": "WebPart",
  "version": "*",
  "manifestVersion": 2,
  "requiresCustomScript": false,
  "supportedHosts": [
    "SharePointWebPart",
    "SharePointFullPage"
  ],
  "supportsFullBleed": true,
  "preconfiguredEntries": [
    {
      "groupId": "5c03119e-3074-46fd-976b-c60198311f70",
      "group": {
        "default": "IT Operations"
      },
      "title": {
        "default": "Cloud Platform Page"
      },
      "description": {
        "default": "AWS or Azure platform documentation page with sidebar navigation"
      },
      "officeFabricIconFontName": "Cloud",
      "properties": {
        "platform": "aws",
        "customStats": ""
      }
    }
  ]
}
